MANIFEST.in
README.rst
setup.py
django_view_perms.egg-info/PKG-INFO
django_view_perms.egg-info/SOURCES.txt
django_view_perms.egg-info/dependency_links.txt
django_view_perms.egg-info/not-zip-safe
django_view_perms.egg-info/requires.txt
django_view_perms.egg-info/top_level.txt
view_perms/__init__.py
view_perms/admin.py
view_perms/apps.py
view_perms/models.py
view_perms/tests.py
view_perms/views.py
view_perms/management/__init__.py
view_perms/middleware/__init__.py
view_perms/middleware/check_view_perm.py
view_perms/migrations/__init__.py